setup.py
distributions_aws_123456/Binomialdistribution.py
distributions_aws_123456/Gaussiandistribution.py
distributions_aws_123456/Generaldistribution.py
distributions_aws_123456/__init__.py
distributions_aws_123456.egg-info/PKG-INFO
distributions_aws_123456.egg-info/SOURCES.txt
distributions_aws_123456.egg-info/dependency_links.txt
distributions_aws_123456.egg-info/not-zip-safe
distributions_aws_123456.egg-info/top_level.txt