Metadata-Version: 1.0
Name: distributions-aws-123456
Version: 0.2
Summary: Gaussian distributions
Home-page: UNKNOWN
Author: AWS_UDACITY
Author-email: mexample@something.com
License: UNKNOWN
Platform: UNKNOWN
